ynlib/data_gradebar.py
ynlibpackages/data_gradebar.py
ynlibpackages-0.1.0.dist-info/METADATA
ynlibpackages-0.1.0.dist-info/WHEEL
ynlibpackages-0.1.0.dist-info/top_level.txt
ynlibpackages-0.1.0.dist-info/RECORD
